signalflow.so
signalflow-stubs/__init__.py
signalflow-stubs/signalflow.pyi
signalflow.libs/libFLAC-206e6ad0.so.12.0.0
signalflow.libs/libfftw3f-cc5eee1f.so.3.6.10
signalflow.libs/libmp3lame-75fc8d8c.so.0.0.0
signalflow.libs/libmpg123-fed015c0.so.0.47.0
signalflow.libs/libogg-06cdba8c.so.0.8.5
signalflow.libs/libopus-70eda5b4.so.0.8.0
signalflow.libs/libsndfile-e2de1c05.so.1.0.35
signalflow.libs/libvorbis-7a473927.so.0.4.9
signalflow.libs/libvorbisenc-8393e8bb.so.2.0.12
signalflow_analysis/__init__.py
signalflow_analysis/audio_feature_buffer.py
signalflow_cli/__init__.py
signalflow_examples/__init__.py
signalflow_examples/signalflow_examples.py
signalflow_midi/__init__.py
signalflow_midi/signalflow_midi.py
signalflow_visualisation/__init__.py
signalflow_visualisation/buffer.py
signalflow_visualisation/node.py
signalflow_visualisation/patch_structure.py
signalflow_vscode/__init__.py
signalflow-0.5.4.dist-info/METADATA
signalflow-0.5.4.dist-info/WHEEL
signalflow-0.5.4.dist-info/entry_points.txt
signalflow-0.5.4.dist-info/top_level.txt
signalflow-0.5.4.dist-info/RECORD
signalflow-0.5.4.dist-info/licenses/LICENSE.md
