Metadata-Version: 2.1
Name: signalflow
Version: 0.5.4
Summary: SignalFlow is a sound synthesis library designed for clear and concise expression of sonic ideas
Author: Daniel Jones
Author-email: dan@erase.net
Keywords: audio,sound,synthesis,dsp,sound-synthesis
Classifier: Topic :: Multimedia :: Sound/Audio
Classifier: Topic :: Multimedia :: Sound/Audio :: Sound Synthesis
Classifier: Topic :: Artistic Software
Classifier: Development Status :: 4 - Beta
Classifier: Intended Audience :: Developers
Requires-Python: >=3.8
License-File: LICENSE.md
Requires-Dist: numpy
Provides-Extra: test
Requires-Dist: pytest; extra == "test"
Requires-Dist: numpy; extra == "test"
Requires-Dist: scipy; extra == "test"
